README.rst
setup.py
PyBaiduYuyin/__init__.py
PyBaiduYuyin.egg-info/PKG-INFO
PyBaiduYuyin.egg-info/SOURCES.txt
PyBaiduYuyin.egg-info/dependency_links.txt
PyBaiduYuyin.egg-info/top_level.txt