Metadata-Version: 1.0
Name: PyBaiduYuyin
Version: 0.1.1
Summary: Library for performing speech recognition with Baidu Speech Recognition API.
Home-page: https://github.com/DelightRun/PyBaiduYuyin
Author: Changxu Wang
Author-email: Changxu.mail@gmail.com
License: BSD
Keywords: baidu voice service
Platform: UNKNOWN
